{
  "owner": "Axodus",
  "repo": "Axodus/AragonOSX",
  "localPath": "/opt/AragonOSX",
  "enableProjectSync": false,
  "gitissuer": {
    "enabled": true,
    "autoDeploy": false,
    "watch": {
      "enabled": true
    },
    "hierarchy": {
      "parentIssueNumber": 123
    }
  },
  "defaults": {
    "defaultEstimateHours": 2,
    "defaultPriority": "HIGH",
    "defaultStatus": "TODO",
    "defaultStartDate": "TBD",
    "defaultEndDate": "TBD",
    "defaultLabels": [
      "plan",
      "osx"
    ]
  }
}
